mtglearn/__init__.py
mtglearn/config.py
mtglearn/version.py
mtglearn/datasets/__init__.py
mtglearn/datasets/cards.py
mtglearn/datasets/rules.py
mtglearn/datasets/utils.py
mtglearn-22.1.0.dev4.dist-info/LICENSE
mtglearn-22.1.0.dev4.dist-info/METADATA
mtglearn-22.1.0.dev4.dist-info/WHEEL
mtglearn-22.1.0.dev4.dist-info/top_level.txt
mtglearn-22.1.0.dev4.dist-info/RECORD
