Metadata-Version: 2.1
Name: mtglearn
Version: 22.1.0.dev4
Summary: Magic the Gathering and Machine Learning
Home-page: https://github.com/dconathan/mtglearn
Author: Devin Conathan
Author-email: dconathan@gmail.com
License: UNKNOWN
Project-URL: Bug Tracker, https://github.com/dconathan/mtglearn/issues
Platform: UNKNOWN
Classifier: Programming Language :: Python :: 3
Classifier: License :: OSI Approved :: Apache Software License
Classifier: Operating System :: OS Independent
Requires-Dist: ftfy
Requires-Dist: datasets
Requires-Dist: attrs
Requires-Dist: cattrs
Provides-Extra: docs
Requires-Dist: mkdocs ; extra == 'docs'
Requires-Dist: mkdocs-material ; extra == 'docs'
Requires-Dist: mkdocstrings ; extra == 'docs'
Requires-Dist: pytkdocs ; extra == 'docs'
Provides-Extra: models
Requires-Dist: torch ; extra == 'models'
Requires-Dist: transformers ; extra == 'models'
Provides-Extra: tests
Requires-Dist: pytest ; extra == 'tests'
